README
setup.py
pycml/__init__.py
pycml/pycml.py
pycml/version.py
pycml.egg-info/PKG-INFO
pycml.egg-info/SOURCES.txt
pycml.egg-info/dependency_links.txt
pycml.egg-info/requires.txt
pycml.egg-info/top_level.txt
pycml/conventions/__init__.py
pycml/conventions/simple_comp_chem.py
test/__init__.py
test/test_pycml.py
test/test_simple_comp_chem.py