Metadata-Version: 1.0
Name: pycml
Version: 0.1.1
Summary: Python Library to support writing Chemical Markup Language documents
Home-page: https://github.com/cameronneylon/pycml
Author: Cameron Neylon
Author-email: pypi@cameroneylon.net
License: UNKNOWN
Platform: UNKNOWN
